{"nodes": [{"id": "docs_ref_actuator_brief_actuator_brief", "label": "Actuator & Driver Electronics Brief", "file_type": "paper", "source_file": "docs/REF_actuator_brief.md", "source_location": null, "source_url": null, "captured_at": null, "author": null, "contributor": null}, {"id": "docs_ref_actuator_brief_amplitude_decoupled_waveform", "label": "Amplitude-Decoupled Waveform Requirement", "file_type": "rationale", "source_file": "docs/REF_actuator_brief.md", "source_location": null, "source_url": null, "captured_at": null, "author": null, "contributor": null}, {"id": "docs_ref_actuator_brief_erm", "label": "ERM (Eccentric Rotating Mass)", "file_type": "concept", "source_file": "docs/REF_actuator_brief.md", "source_location": null, "source_url": null, "captured_at": null, "author": null, "contributor": null}, {"id": "docs_ref_actuator_brief_lra", "label": "LRA (Linear Resonant Actuator)", "file_type": "concept", "source_file": "docs/REF_actuator_brief.md", "source_location": null, "source_url": null, "captured_at": null, "author": null, "contributor": null}, {"id": "docs_ref_actuator_brief_voice_coil_exciter", "label": "Voice-Coil Exciter (DAEX Family)", "file_type": "concept", "source_file": "docs/REF_actuator_brief.md", "source_location": null, "source_url": null, "captured_at": null, "author": null, "contributor": null}, {"id": "docs_ref_actuator_brief_bass_shaker_tt25", "label": "Bass Shaker (TT25 Puck)", "file_type": "concept", "source_file": "docs/REF_actuator_brief.md", "source_location": null, "source_url": null, "captured_at": null, "author": null, "contributor": null}, {"id": "docs_ref_actuator_brief_piezo_powerhap", "label": "Piezo (TDK PowerHap)", "file_type": "concept", "source_file": "docs/REF_actuator_brief.md", "source_location": null, "source_url": null, "captured_at": null, "author": null, "contributor": null}, {"id": "docs_ref_actuator_brief_drv2605l", "label": "TI DRV2605L Haptic Driver", "file_type": "concept", "source_file": "docs/REF_actuator_brief.md", "source_location": null, "source_url": null, "captured_at": null, "author": null, "contributor": null}, {"id": "docs_ref_actuator_brief_classd_amps", "label": "Class-D Audio Amps (PAM8403/MAX98357A)", "file_type": "concept", "source_file": "docs/REF_actuator_brief.md", "source_location": null, "source_url": null, "captured_at": null, "author": null, "contributor": null}, {"id": "docs_ref_actuator_brief_teensy_audio", "label": "Teensy 4.x + Audio Library (TDM)", "file_type": "concept", "source_file": "docs/REF_actuator_brief.md", "source_location": null, "source_url": null, "captured_at": null, "author": null, "contributor": null}, {"id": "docs_ref_actuator_brief_latency_budget", "label": "Latency Budget (Haptic Lags Audio)", "file_type": "concept", "source_file": "docs/REF_actuator_brief.md", "source_location": null, "source_url": null, "captured_at": null, "author": null, "contributor": null}, {"id": "docs_ref_actuator_brief_sensory_funneling", "label": "Sensory Funneling (Phantom Locations)", "file_type": "concept", "source_file": "docs/REF_actuator_brief.md", "source_location": null, "source_url": null, "captured_at": null, "author": null, "contributor": null}, {"id": "docs_ref_actuator_brief_lofelt_actronika", "label": "Lofelt L5 / Actronika HapCoil-One", "file_type": "concept", "source_file": "docs/REF_actuator_brief.md", "source_location": null, "source_url": null, "captured_at": null, "author": null, "contributor": null}], "edges": [{"source": "docs_ref_actuator_brief_actuator_brief", "target": "docs_ref_actuator_brief_amplitude_decoupled_waveform", "relation": "references", "confidence": "EXTRACTED", "confidence_score": 1.0, "source_file": "docs/REF_actuator_brief.md", "source_location": null, "weight": 1.0}, {"source": "docs_ref_actuator_brief_amplitude_decoupled_waveform", "target": "docs_ref_actuator_brief_erm", "relation": "rationale_for", "confidence": "EXTRACTED", "confidence_score": 1.0, "source_file": "docs/REF_actuator_brief.md", "source_location": null, "weight": 1.0}, {"source": "docs_ref_actuator_brief_amplitude_decoupled_waveform", "target": "docs_ref_actuator_brief_voice_coil_exciter", "relation": "rationale_for", "confidence": "EXTRACTED", "confidence_score": 1.0, "source_file": "docs/REF_actuator_brief.md", "source_location": null, "weight": 1.0}, {"source": "docs_ref_actuator_brief_actuator_brief", "target": "docs_ref_actuator_brief_lra", "relation": "references", "confidence": "EXTRACTED", "confidence_score": 1.0, "source_file": "docs/REF_actuator_brief.md", "source_location": null, "weight": 1.0}, {"source": "docs_ref_actuator_brief_actuator_brief", "target": "docs_ref_actuator_brief_voice_coil_exciter", "relation": "references", "confidence": "EXTRACTED", "confidence_score": 1.0, "source_file": "docs/REF_actuator_brief.md", "source_location": null, "weight": 1.0}, {"source": "docs_ref_actuator_brief_actuator_brief", "target": "docs_ref_actuator_brief_bass_shaker_tt25", "relation": "references", "confidence": "EXTRACTED", "confidence_score": 1.0, "source_file": "docs/REF_actuator_brief.md", "source_location": null, "weight": 1.0}, {"source": "docs_ref_actuator_brief_actuator_brief", "target": "docs_ref_actuator_brief_piezo_powerhap", "relation": "references", "confidence": "EXTRACTED", "confidence_score": 1.0, "source_file": "docs/REF_actuator_brief.md", "source_location": null, "weight": 1.0}, {"source": "docs_ref_actuator_brief_voice_coil_exciter", "target": "docs_ref_actuator_brief_classd_amps", "relation": "shares_data_with", "confidence": "EXTRACTED", "confidence_score": 1.0, "source_file": "docs/REF_actuator_brief.md", "source_location": null, "weight": 1.0}, {"source": "docs_ref_actuator_brief_lra", "target": "docs_ref_actuator_brief_drv2605l", "relation": "shares_data_with", "confidence": "EXTRACTED", "confidence_score": 1.0, "source_file": "docs/REF_actuator_brief.md", "source_location": null, "weight": 1.0}, {"source": "docs_ref_actuator_brief_actuator_brief", "target": "docs_ref_actuator_brief_teensy_audio", "relation": "references", "confidence": "EXTRACTED", "confidence_score": 1.0, "source_file": "docs/REF_actuator_brief.md", "source_location": null, "weight": 1.0}, {"source": "docs_ref_actuator_brief_actuator_brief", "target": "docs_ref_actuator_brief_latency_budget", "relation": "references", "confidence": "EXTRACTED", "confidence_score": 1.0, "source_file": "docs/REF_actuator_brief.md", "source_location": null, "weight": 1.0}, {"source": "docs_ref_actuator_brief_actuator_brief", "target": "docs_ref_actuator_brief_sensory_funneling", "relation": "references", "confidence": "EXTRACTED", "confidence_score": 1.0, "source_file": "docs/REF_actuator_brief.md", "source_location": null, "weight": 1.0}, {"source": "docs_ref_actuator_brief_actuator_brief", "target": "docs_ref_actuator_brief_lofelt_actronika", "relation": "cites", "confidence": "EXTRACTED", "confidence_score": 1.0, "source_file": "docs/REF_actuator_brief.md", "source_location": null, "weight": 1.0}, {"source": "docs_ref_actuator_brief_sensory_funneling", "target": "docs_ref_psychophysics_brief_israr_poupyrev_2011", "relation": "cites", "confidence": "EXTRACTED", "confidence_score": 1.0, "source_file": "docs/REF_actuator_brief.md", "source_location": null, "weight": 1.0}, {"source": "docs_ref_actuator_brief_voice_coil_exciter", "target": "docs_14_hardware_integration_voice_coil_exciter", "relation": "conceptually_related_to", "confidence": "INFERRED", "confidence_score": 0.9, "source_file": "docs/REF_actuator_brief.md", "source_location": null, "weight": 1.0}, {"source": "docs_ref_actuator_brief_sensory_funneling", "target": "docs_12_perception_references_funneling_saltation", "relation": "semantically_similar_to", "confidence": "INFERRED", "confidence_score": 0.9, "source_file": "docs/REF_actuator_brief.md", "source_location": null, "weight": 1.0}], "hyperedges": []}